emojipy/__init__.py
emojipy/emojipy.py
emojipy/unicode.py
emojipyy/__init__.py
emojipyy/emojipyy.py
emojipyy/unicode.py
tests/__init__.py
tests/test_emojipy.py
emojipyy-1.0.2.1.dist-info/METADATA
emojipyy-1.0.2.1.dist-info/WHEEL
emojipyy-1.0.2.1.dist-info/top_level.txt
emojipyy-1.0.2.1.dist-info/RECORD
