Metadata-Version: 2.1
Name: emojipyy
Version: 1.0.2.1
Summary: emoji for Python
Home-page: UNKNOWN
Author: MGF15
Author-email: UNKNOWN
License: MIT
Platform: UNKNOWN
